vrw/__init__.py
vrw/reader.py
vrw/writer.py
vrw/_reader_backends/__init__.py
vrw/_reader_backends/base.py
vrw/_reader_backends/cv2_backend.py
vrw/_reader_backends/rust_backend.py
vrw/_writer_backends/__init__.py
vrw/_writer_backends/base.py
vrw/_writer_backends/cv2_backend.py
vrw/_writer_backends/pyav_backend.py
vrw-0.2.0.dist-info/METADATA
vrw-0.2.0.dist-info/WHEEL
vrw-0.2.0.dist-info/licenses/LICENSE
vrw-0.2.0.dist-info/RECORD
