Metadata-Version: 2.4
Name: vrw
Version: 0.2.0
Summary: Library for simple video reading and writing
Author-email: tkclam <thomas.lam@epfl.ch>
License-File: LICENSE
Requires-Python: >=3.12
Requires-Dist: av>=16
Requires-Dist: opencv-python>=4
Requires-Dist: video-reader-rs>=0.3.0
